pytopplot/__init__.py
pytopplot/__main__.py
pytopplot/version.py
pytopplot/abci/Linux/abci.exe
pytopplot/abci/Windows/abci.exe
pytopplot/generator/generator.py
pytopplot/parse/parser.py
pytopplot/ui/alert.ui
pytopplot/ui/dialog.ui
pytopplot/ui/progress.ui
pytopplot/ui/window.py
pytopplot/ui/window.ui
pytopplot-21.7.dist-info/LICENSE
pytopplot-21.7.dist-info/METADATA
pytopplot-21.7.dist-info/WHEEL
pytopplot-21.7.dist-info/entry_points.txt
pytopplot-21.7.dist-info/top_level.txt
pytopplot-21.7.dist-info/RECORD
